{"title":"AE 7: Exam 2 Review","markdown":{"yaml":{"title":"AE 7: Exam 2 Review"},"headingText":"Packages","containsRefs":false,"markdown":"\n\n::: callout-important\nGo to the [course GitHub organization](https://github.com/sta210-s22) and locate the repo titled `ae-7-exam-2-review-YOUR_GITHUB_USERNAME` to get started.\n:::\n\n\n```{r}\n#| label: load-pkgs\n#| message: false\n \nlibrary(tidyverse)\nlibrary(tidymodels)\nlibrary(knitr)\nlibrary(openintro)\n\n# fix data!\nloans_full_schema <- droplevels(loans_full_schema)\n```\n\n## Goal\n\nCreate a model for precicting `interest_rate`.\n\n## View data\n\nNote the dimensions of the data and the variable names.\nReview the data dictionary.\n\n```{r}\n#| label: load-data\n\n# add code here\n```\n\n## Split data into training and testing\n\nSplit your data into testing and training sets.\n\n```{r}\n#| label: initial-split\n\n# add code here\n```\n\n## Write the model\n\nWrite the model for predicting interest rate (`interest_rate`) from debt to income ratio (`debt_to_income`), the term of loan (`term`), the number of inquiries (credit checks) into the applicant's credit during the last 12 months (`inquiries_last_12m`), whether there are any bankruptcies listed in the public record for this applicant (`bankrupt`), and the type of application (`application_type`).\nThe model should allow for the effect of to income ratio on interest rate to vary by application type.\n\n*Add model here*\n\n## Exploration\n\nExplore characteristics of the variables you'll use for the model using the training data only.\n\n```{r}\n#| label: explore\n\n# add code here\n```\n\n## Specify model\n\nSpecify a linear regression model.\nCall it `office_spec`.\n\n```{r}\n#| label: specify-model\n\n# add code here\n```\n\n## Create recipe\n\n-   Predict `interest_rate` from `debt_to_income`, `term`, `inquiries_last_12m`, `public_record_bankrupt`, and `application_type`.\n-   Mean center `debt_to_income`.\n-   Make `term` a factor.\n-   Create a new variable: `bankrupt` that takes on the value \"no\" if `public_record_bankrupt` is 0 and the value \"yes\" if `public_record_bankrupt` is 1 or higher. Then, remove `public_record_bankrupt`.\n-   Interact `application_type` with `debt_to_income`.\n-   Create dummy variables where needed and drop any zero variance variables.\n\n```{r}\n#| label: create-recipe\n\n# add code here\n```\n\n## Create workflow\n\nCreate the workflow that brings together the model specification and recipe.\n\n```{r}\n#| label: create-wflow\n\n# add code here\n```\n\n## Cross validation\n\nConduct 10-fold cross validation.\n\n```{r}\n#| label: cv-tenfold\n\n# add code here\n```\n\n## Summarize CV metrics\n\nSummarize metrics from your CV resamples.\n\n```{r}\n#| label: cv-summarize\n\n# add code here\n```\n\nWhy are we focusing on R-squared and RMSE instead of adjusted R-squared, AIC, BIC?\n\n*\\[Add response here\\]*\n\n## Next steps...\n\nDepending on time, either\n\n-   Create a workflow for another model with a new recipe (omitting the interaction variable), conduct CV, do model selection between these two, and then interpret the coefficients for the selected model.\n-   Or interpret the coefficients for the one model you fit.\n\nMake sure to interpret the intercept and slope coefficient for at least one numerical, one categorical, and one interaction predictor.\n"},"formats":{"html":{"execute":{"fig-width":7,"fig-height":5,"fig-format":"retina","fig-dpi":96,"error":false,"eval":true,"cache":null,"freeze":"auto","echo":true,"output":true,"warning":true,"include":true,"keep-md":false,"keep-ipynb":false,"ipynb":null,"enabled":null,"daemon":null,"daemon-restart":false,"debug":false,"ipynb-filters":[],"engine":"knitr"},"render":{"keep-tex":false,"keep-yaml":false,"keep-source":false,"keep-hidden":false,"prefer-html":false,"output-divs":true,"output-ext":"html","fig-align":"default","fig-pos":null,"fig-env":null,"code-fold":"none","code-overflow":"wrap","code-link":false,"code-line-numbers":false,"code-tools":false,"tbl-colwidths":"auto","merge-includes":true,"latex-auto-mk":true,"latex-auto-install":true,"latex-clean":true,"latex-max-runs":10,"latex-makeindex":"makeindex","latex-makeindex-opts":[],"latex-tlmgr-opts":[],"latex-input-paths":[],"latex-output-dir":null,"link-external-icon":false,"link-external-newwindow":false},"pandoc":{"standalone":true,"wrap":"none","default-image-extension":"png","to":"html","toc":true,"output-file":"ae-7-exam-2-review.html"},"language":{},"metadata":{"lang":"en","fig-responsive":true,"quarto-version":"0.9.345","editor":"visual","theme":{"light":["cosmo","../theme.scss"],"dark":["cosmo","../theme-dark.scss"]},"mainfont":"Atkinson Hyperlegible","code-copy":true,"title":"AE 7: Exam 2 Review"},"extensions":{"book":{"multiFile":true}}}}}