{"title":"Exam 2 review","markdown":{"yaml":{"title":"Exam 2 review","subtitle":"STA 210 - Spring 2022","author":"Dr. Mine Çetinkaya-Rundel","footer":"[sta210-s22.github.io/website](https://sta210-s22.github.io/website/)","logo":"images/logo.png","format":{"revealjs":{"theme":"slides.scss","transition":"fade","slide-number":true,"incremental":true,"chalkboard":true}},"editor":"visual","execute":{"freeze":"auto","echo":true}},"headingText":"Announcements","containsRefs":false,"markdown":"\n\n\n::: nonincremental\n-   Exam 2 is released tomorrow (Friday) at 9am, due at 11:59pm on Monday\n-   Keys for HW and labs posted\n:::\n\n## Application exercise\n\n::: appex\n📋 [github.com/sta210-s22/ae-7-exam-2-review](https://github.com/sta210-s22/ae-7-exam-2-review)\n:::\n"},"formats":{"revealjs":{"execute":{"fig-width":10,"fig-height":5,"fig-format":"retina","fig-dpi":96,"error":false,"eval":true,"cache":null,"freeze":"auto","echo":true,"output":true,"warning":false,"include":true,"keep-md":false,"keep-ipynb":false,"ipynb":null,"enabled":null,"daemon":null,"daemon-restart":false,"debug":false,"ipynb-filters":[],"engine":"markdown"},"render":{"keep-tex":false,"keep-yaml":false,"keep-source":false,"keep-hidden":false,"prefer-html":false,"output-divs":true,"output-ext":"html","fig-align":"default","fig-pos":null,"fig-env":null,"code-fold":"none","code-overflow":"scroll","code-link":false,"code-line-numbers":true,"code-tools":false,"tbl-colwidths":"auto","merge-includes":true,"latex-auto-mk":true,"latex-auto-install":true,"latex-clean":true,"latex-max-runs":10,"latex-makeindex":"makeindex","latex-makeindex-opts":[],"latex-tlmgr-opts":[],"latex-input-paths":[],"latex-output-dir":null,"link-external-icon":false,"link-external-newwindow":false},"pandoc":{"standalone":true,"wrap":"none","default-image-extension":"png","html-math-method":{"method":"mathjax","url":"https://cdnjs.cloudflare.com/ajax/libs/mathjax/2.7.0/MathJax.js?config=TeX-AMS_HTML-full"},"slide-level":2,"to":"revealjs","incremental":true,"output-file":"lec-15.html"},"language":{},"metadata":{"lang":"en","fig-responsive":false,"quarto-version":"0.9.345","auto-stretch":true,"editor":"visual","title":"Exam 2 review","subtitle":"STA 210 - Spring 2022","author":"Dr. Mine Çetinkaya-Rundel","footer":"[sta210-s22.github.io/website](https://sta210-s22.github.io/website/)","logo":"images/logo.png","theme":"slides.scss","transition":"fade","slideNumber":true,"chalkboard":true}}}}